Metadata-Version: 2.1
Name: aws-glue-workflow-analyzer
Version: 1.0.0
Home-page: https://github.com/victor-mariano-leite/aws-glue-workflow-analyzer
Author: Victor Mariano Leite
Author-email: marianoleite44@gmail.com
License-File: LICENSE
Requires-Dist: boto3 ==1.33.*
Requires-Dist: moto ==4.2.*
Requires-Dist: pytest ==7.4.*
Requires-Dist: rich[all] ==13.7.*
Requires-Dist: pytest-mock
Requires-Dist: pytest-cov
Requires-Dist: pyparsing
